unpoly/__init__.py
unpoly/forms.py
unpoly/middleware.py
unpoly/typehints.py
unpoly/unpoly.py
unpoly/views.py
unpoly_django-0.1.0.dist-info/LICENSE
unpoly_django-0.1.0.dist-info/METADATA
unpoly_django-0.1.0.dist-info/WHEEL
unpoly_django-0.1.0.dist-info/top_level.txt
unpoly_django-0.1.0.dist-info/RECORD
