Metadata-Version: 2.1
Name: unpoly-django
Version: 0.1.0
Summary: An app for Django to implement the Unpoly v2 Server Protocol
Home-page: https://github.com/thinkwelltwd/unpoly_django
Author: Dave Burkholder
Author-email: dave@thinkwelldesigns.com
License: MIT License
Keywords: django unpoly
Platform: UNKNOWN
Classifier: Development Status :: 3 - Alpha
Classifier: Intended Audience :: Developers
Classifier: License :: OSI Approved :: MIT License
Classifier: Natural Language :: English
Classifier: Programming Language :: Python :: 3.8
Classifier: Programming Language :: Python :: 3.9
Classifier: Framework :: Django
Classifier: Framework :: Django :: 3.1
Requires-Dist: Django (>=3.1)
